LICENSE
MANIFEST.in
pywurfl.spec
requirements.txt
setup.py
bin/wurfl2python.py
doc/ChangeLog
doc/README
doc/api/api-objects.txt
doc/api/class-tree.html
doc/api/crarr.png
doc/api/epydoc.css
doc/api/frames.html
doc/api/help.html
doc/api/identifier-index.html
doc/api/index.html
doc/api/module-tree.html
doc/api/pywurfl-module.html
doc/api/pywurfl-pysrc.html
doc/api/pywurfl.Devices-class.html
doc/api/pywurfl.RootDevice-class.html
doc/api/pywurfl.algorithms-module.html
doc/api/pywurfl.algorithms-pysrc.html
doc/api/pywurfl.algorithms.Algorithm-class.html
doc/api/pywurfl.algorithms.JaroWinkler-class.html
doc/api/pywurfl.algorithms.LevenshteinDistance-class.html
doc/api/pywurfl.algorithms.Tokenizer-class.html
doc/api/pywurfl.algorithms.TwoStepAnalysis-class.html
doc/api/pywurfl.algorithms.wurfl-module.html
doc/api/pywurfl.algorithms.wurfl-pysrc.html
doc/api/pywurfl.algorithms.wurfl.handlers-module.html
doc/api/pywurfl.algorithms.wurfl.handlers-pysrc.html
doc/api/pywurfl.algorithms.wurfl.handlers.AOLMatcher-class.html
doc/api/pywurfl.algorithms.wurfl.handlers.AbstractMatcher-class.html
doc/api/pywurfl.algorithms.wurfl.handlers.AlcatelMatcher-class.html
doc/api/pywurfl.algorithms.wurfl.handlers.AndroidMatcher-class.html
doc/api/pywurfl.algorithms.wurfl.handlers.AppleMatcher-class.html
doc/api/pywurfl.algorithms.wurfl.handlers.BenQMatcher-class.html
doc/api/pywurfl.algorithms.wurfl.handlers.BlackberryMatcher-class.html
doc/api/pywurfl.algorithms.wurfl.handlers.BotMatcher-class.html
doc/api/pywurfl.algorithms.wurfl.handlers.CatchAllMatcher-class.html
doc/api/pywurfl.algorithms.wurfl.handlers.ChromeMatcher-class.html
doc/api/pywurfl.algorithms.wurfl.handlers.DoCoMoMatcher-class.html
doc/api/pywurfl.algorithms.wurfl.handlers.FirefoxMatcher-class.html
doc/api/pywurfl.algorithms.wurfl.handlers.GrundigMatcher-class.html
doc/api/pywurfl.algorithms.wurfl.handlers.HTCMatcher-class.html
doc/api/pywurfl.algorithms.wurfl.handlers.KDDIMatcher-class.html
pywurfl.egg-info/PKG-INFO
pywurfl.egg-info/SOURCES.txt
pywurfl.egg-info/dependency_links.txt
pywurfl.egg-info/requires.txt
pywurfl.egg-info/top_level.txt
